adafruit_circuitpython_dps310-2.1.19.dist-info/licenses/LICENSE
adafruit_dps310/__init__.py
adafruit_dps310/advanced.py
adafruit_dps310/basic.py
adafruit_circuitpython_dps310-2.1.19.dist-info/METADATA
adafruit_circuitpython_dps310-2.1.19.dist-info/WHEEL
adafruit_circuitpython_dps310-2.1.19.dist-info/top_level.txt
adafruit_circuitpython_dps310-2.1.19.dist-info/RECORD
